{
    "root": {
        "errorpost": [
            {
                "id": 1965075,
                "event": 0,
                "txType": 2,
                "tx": "此兑换码仅能在页游上进行兑换！"
            },
            {
                "id": 1965076,
                "event": 0,
                "txType": 2,
                "tx": "此兑换码仅能在H5上进行兑换！"
            },
            {
                "id": 1965079,
                "event": 0,
                "txType": 2,
                "tx": "出战背包中有不可挑战的精灵！"
            },
            {
                "id": 1965080,
                "event": 0,
                "txType": 2,
                "tx": "不符合兑换条件！"
            },
            {
                "id": 1965081,
                "event": 0,
                "txType": 2,
                "tx": "精力值不足！"
            },
            {
                "id": 1965082,
                "event": 0,
                "txType": 2,
                "tx": "所有道具已拥有！"
            },
            {
                "id": 1965086,
                "event": 0,
                "txType": 2,
                "tx": "仅限2023年11月23日-2024年2月23日创建的新角色可使用！"
            },
            {
                "id": 1965087,
                "event": 0,
                "txType": 2,
                "tx": "请按照需求使用规划版完成事件！"
            },
            {
                "id": 1965088,
                "event": 0,
                "txType": 2,
                "tx": "没有可以完成的战队任务！"
            },
            {
                "id": 1965089,
                "event": 0,
                "txType": 2,
                "tx": "仓库里符合要求的精灵数量不足！"
            },
            {
                "id": 1965090,
                "event": 0,
                "txType": 2,
                "tx": "不能退出战队，还有未完成的战队任务！"
            },
            {
                "id": 1965091,
                "event": 0,
                "txType": 2,
                "tx": "您的段位还未到出世天骄或以上，还不能进行ban位投票哦！"
            },
            {
                "id": 1965092,
                "event": 0,
                "txType": 2,
                "tx": "你已装备了1个专属刻印，同一只精灵只能装备1个专属刻印哦！"
            },
            {
                "id": 1965093,
                "event": 0,
                "txType": 2,
                "tx": "你已装备了相同的刻印或者同一系列的2个刻印！"
            },
            {
                "id": 1965097,
                "event": 0,
                "txType": 2,
                "tx": "该精灵当前没有战队加成！"
            },
            {
                "id": 1965098,
                "event": 0,
                "txType": 2,
                "tx": "当前回溯请求频繁，请稍后再试，或通过kf.61.com联系客服。"
            },
            {
                "id": 1965101,
                "event": 0,
                "txType": 2,
                "tx": "生成能源超过数量限制"
            },
            {
                "id": 1965102,
                "event": 0,
                "txType": 2,
                "tx": "生成能源类型与目标不符"
            },
            {
                "id": 1965103,
                "event": 0,
                "txType": 2,
                "tx": "转换过程中没有匹配到对应能源"
            },
            {
                "id": 1965105,
                "event": 0,
                "txType": 2,
                "tx": "牌库中已经没有剩余的牌了！"
            },
            {
                "id": 1965107,
                "event": 0,
                "txType": 2,
                "tx": "因违反用户协议，禁止参与竞技模式对战至10月31日0点"
            },
            {
                "id": 1965109,
                "event": 0,
                "txType": 2,
                "tx": "购买过于频繁，请前往其他区域进行交易。"
            },
            {
                "id": 1965111,
                "event": 0,
                "txType": 2,
                "tx": "精灵觉醒不能使用限制精灵。"
            },
            {
                "id": 1965112,
                "event": 0,
                "txType": 2,
                "tx": "精灵觉醒不能使用重复精灵。"
            },
            {
                "id": 1965113,
                "event": 0,
                "txType": 2,
                "tx": "请先获取觉醒精灵的专属特性和第五技能。"
            },
            {
                "id": 1965114,
                "event": 0,
                "txType": 2,
                "tx": "无法在此列释放气团！"
            },
            {
                "id": 1965115,
                "event": 0,
                "txType": 2,
                "tx": "此兑换码仅能在Unity上进行兑换！"
            }
        ]
    }
}