{
    "data": [
        {
            "id": 1,
            "activityid": 1,
            "activityname": "0403纳多雷的复苏之旅",
            "title": "",
            "describe": "今日完成1次复苏之旅挑战",
            "tasktype": 0,
            "value": 1,
            "time": 1,
            "time2": "",
            "timelimit": "1",
            "timestart": "1743645600",
            "timeend": "1744941600",
            "rewardinfo": "1_1726973_10",
            "userinfo": 210008,
            "userbitbuf": 1000642,
            "stat": 2504020100
        },
        {
            "id": 2,
            "activityid": 1,
            "activityname": "0403纳多雷的复苏之旅",
            "title": "",
            "describe": "今日复苏之旅中累计达到1000分",
            "tasktype": 0,
            "value": 1000,
            "time": 1,
            "time2": "",
            "timelimit": "1",
            "timestart": "1743645600",
            "timeend": "1744941600",
            "rewardinfo": "1_1726973_20",
            "userinfo": 210009,
            "userbitbuf": 1000643,
            "stat": 2504020101
        },
        {
            "id": 3,
            "activityid": 1,
            "activityname": "0403纳多雷的复苏之旅",
            "title": "",
            "describe": "在复苏之旅中累计达到3000分",
            "tasktype": 0,
            "value": 3000,
            "time": 0,
            "time2": "",
            "timelimit": "1",
            "timestart": "1743645600",
            "timeend": "1744941600",
            "rewardinfo": "1_1726973_30",
            "userinfo": 211013,
            "userbitbuf": 12254,
            "stat": 2504020102
        },
        {
            "id": 4,
            "activityid": 1,
            "activityname": "0403纳多雷的复苏之旅",
            "title": "",
            "describe": "在复苏之旅中累计达到5000分",
            "tasktype": 0,
            "value": 5000,
            "time": 0,
            "time2": "",
            "timelimit": "1",
            "timestart": "1743645600",
            "timeend": "1744941600",
            "rewardinfo": "1_1726973_30",
            "userinfo": 211013,
            "userbitbuf": 12255,
            "stat": 2504020103
        },
        {
            "id": 5,
            "activityid": 1,
            "activityname": "0403纳多雷的复苏之旅",
            "title": "",
            "describe": "在复苏之旅中累计达到10000分",
            "tasktype": 0,
            "value": 10000,
            "time": 0,
            "time2": "",
            "timelimit": "1",
            "timestart": "1743645600",
            "timeend": "1744941600",
            "rewardinfo": "1_1726973_30",
            "userinfo": 211013,
            "userbitbuf": 12256,
            "stat": 2504020104
        },
        {
            "id": 6,
            "activityid": 1,
            "activityname": "0403纳多雷的复苏之旅",
            "title": "",
            "describe": "单次复苏之旅中获得500分及以上",
            "tasktype": 0,
            "value": 500,
            "time": 0,
            "time2": "",
            "timelimit": "1",
            "timestart": "1743645600",
            "timeend": "1744941600",
            "rewardinfo": "1_1726973_30",
            "userinfo": 211014,
            "userbitbuf": 12257,
            "stat": 2504020105
        },
        {
            "id": 7,
            "activityid": 1,
            "activityname": "0403纳多雷的复苏之旅",
            "title": "",
            "describe": "单次复苏之旅中获得750分及以上",
            "tasktype": 0,
            "value": 750,
            "time": 0,
            "time2": "",
            "timelimit": "1",
            "timestart": "1743645600",
            "timeend": "1744941600",
            "rewardinfo": "1_1726973_30",
            "userinfo": 211014,
            "userbitbuf": 12258,
            "stat": 2504020106
        },
        {
            "id": 8,
            "activityid": 1,
            "activityname": "0403纳多雷的复苏之旅",
            "title": "",
            "describe": "单次复苏之旅中获得1000分及以上",
            "tasktype": 0,
            "value": 1000,
            "time": 0,
            "time2": "",
            "timelimit": "1",
            "timestart": "1743645600",
            "timeend": "1744941600",
            "rewardinfo": "1_1726973_30",
            "userinfo": 211014,
            "userbitbuf": 12259,
            "stat": 2504020107
        },
        {
            "id": 9,
            "activityid": 1,
            "activityname": "0403纳多雷的复苏之旅",
            "title": "",
            "describe": "在复苏之旅中成功合成1次生命标志",
            "tasktype": 0,
            "value": 1,
            "time": 0,
            "time2": "",
            "timelimit": "1",
            "timestart": "1743645600",
            "timeend": "1744941600",
            "rewardinfo": "1_1726973_20",
            "userinfo": 211015,
            "userbitbuf": 12260,
            "stat": 2504020108
        },
        {
            "id": 10,
            "activityid": 1,
            "activityname": "0403纳多雷的复苏之旅",
            "title": "",
            "describe": "在复苏之旅中成功将一个温泉口强化到3级（满级）",
            "tasktype": 0,
            "value": 1,
            "time": 0,
            "time2": "",
            "timelimit": "1",
            "timestart": "1743645600",
            "timeend": "1744941600",
            "rewardinfo": "1_1726973_20",
            "userinfo": 211016,
            "userbitbuf": 12261,
            "stat": 2504020109
        },
        {
            "id": 11,
            "activityid": 1,
            "activityname": "0403纳多雷的复苏之旅",
            "title": "",
            "describe": "在复苏之旅中成功改造一个温泉口的产出资源",
            "tasktype": 0,
            "value": 1,
            "time": 0,
            "time2": "",
            "timelimit": "1",
            "timestart": "1743645600",
            "timeend": "1744941600",
            "rewardinfo": "1_1726973_20",
            "userinfo": 211017,
            "userbitbuf": 12262,
            "stat": 2504020110
        },
        {
            "id": 12,
            "activityid": 1,
            "activityname": "0403纳多雷的复苏之旅",
            "title": "",
            "describe": "在复苏之旅中成功战胜1次大型灾厄",
            "tasktype": 0,
            "value": 1,
            "time": 0,
            "time2": "",
            "timelimit": "1",
            "timestart": "1743645600",
            "timeend": "1744941600",
            "rewardinfo": "1_1726973_20",
            "userinfo": 211018,
            "userbitbuf": 12263,
            "stat": 2504020111
        },
        {
            "id": 18,
            "activityid": 1,
            "activityname": "0403纳多雷的复苏之旅",
            "title": "",
            "describe": "在游戏结算时触发“未雨绸缪的囤积者”",
            "tasktype": 0,
            "value": 1,
            "time": 0,
            "time2": "",
            "timelimit": "1",
            "timestart": "1743645600",
            "timeend": "1744941600",
            "rewardinfo": "1_1726973_5",
            "userinfo": 211019,
            "userbitbuf": 12264,
            "stat": 2504020112
        },
        {
            "id": 19,
            "activityid": 1,
            "activityname": "0403纳多雷的复苏之旅",
            "title": "",
            "describe": "在游戏结算时触发“见机行事的交易者”",
            "tasktype": 0,
            "value": 1,
            "time": 0,
            "time2": "",
            "timelimit": "1",
            "timestart": "1743645600",
            "timeend": "1744941600",
            "rewardinfo": "1_1726973_5",
            "userinfo": 211020,
            "userbitbuf": 12265,
            "stat": 2504020113
        },
        {
            "id": 20,
            "activityid": 1,
            "activityname": "0403纳多雷的复苏之旅",
            "title": "",
            "describe": "在游戏结算时触发“沸腾的温泉”",
            "tasktype": 0,
            "value": 1,
            "time": 0,
            "time2": "",
            "timelimit": "1",
            "timestart": "1743645600",
            "timeend": "1744941600",
            "rewardinfo": "1_1726973_5",
            "userinfo": 211021,
            "userbitbuf": 12266,
            "stat": 2504020114
        },
        {
            "id": 21,
            "activityid": 1,
            "activityname": "0403纳多雷的复苏之旅",
            "title": "",
            "describe": "在游戏结算时触发“活跃的温泉”",
            "tasktype": 0,
            "value": 1,
            "time": 0,
            "time2": "",
            "timelimit": "1",
            "timestart": "1743645600",
            "timeend": "1744941600",
            "rewardinfo": "1_1726973_5",
            "userinfo": 211022,
            "userbitbuf": 12267,
            "stat": 2504020115
        },
        {
            "id": 22,
            "activityid": 1,
            "activityname": "0403纳多雷的复苏之旅",
            "title": "",
            "describe": "在游戏结算时触发“不灭的意志”",
            "tasktype": 0,
            "value": 1,
            "time": 0,
            "time2": "",
            "timelimit": "1",
            "timestart": "1743645600",
            "timeend": "1744941600",
            "rewardinfo": "1_1726973_5",
            "userinfo": 211023,
            "userbitbuf": 12268,
            "stat": 2504020116
        },
        {
            "id": 23,
            "activityid": 1,
            "activityname": "0403纳多雷的复苏之旅",
            "title": "",
            "describe": "在游戏结算时触发“强韧的生命”",
            "tasktype": 0,
            "value": 1,
            "time": 0,
            "time2": "",
            "timelimit": "1",
            "timestart": "1743645600",
            "timeend": "1744941600",
            "rewardinfo": "1_1726973_5",
            "userinfo": 211024,
            "userbitbuf": 12269,
            "stat": 2504020117
        },
        {
            "id": 24,
            "activityid": 1,
            "activityname": "0403纳多雷的复苏之旅",
            "title": "",
            "describe": "在灾厄等级2级难度下成功完成1次复苏之旅",
            "tasktype": 0,
            "value": 1,
            "time": 0,
            "time2": "",
            "timelimit": "1",
            "timestart": "1744336800",
            "timeend": "1744941600",
            "rewardinfo": "1_1726973_30",
            "userinfo": 211025,
            "userbitbuf": 12270,
            "stat": 2504020118
        },
        {
            "id": 25,
            "activityid": 1,
            "activityname": "0403纳多雷的复苏之旅",
            "title": "",
            "describe": "在灾厄等级3级难度下成功完成1次复苏之旅",
            "tasktype": 0,
            "value": 1,
            "time": 0,
            "time2": "",
            "timelimit": "1",
            "timestart": "1744336800",
            "timeend": "1744941600",
            "rewardinfo": "1_1726973_30",
            "userinfo": 211026,
            "userbitbuf": 12271,
            "stat": 2504020119
        },
        {
            "id": 26,
            "activityid": 1,
            "activityname": "0403纳多雷的复苏之旅",
            "title": "",
            "describe": "在灾厄等级4级难度下成功完成1次复苏之旅",
            "tasktype": 0,
            "value": 1,
            "time": 0,
            "time2": "",
            "timelimit": "1",
            "timestart": "1744336800",
            "timeend": "1744941600",
            "rewardinfo": "1_1726973_30",
            "userinfo": 211027,
            "userbitbuf": 12272,
            "stat": 2504020120
        },
        {
            "id": 27,
            "activityid": 1,
            "activityname": "0403纳多雷的复苏之旅",
            "title": "",
            "describe": "在灾厄等级5级难度下成功完成1次复苏之旅",
            "tasktype": 0,
            "value": 1,
            "time": 0,
            "time2": "",
            "timelimit": "1",
            "timestart": "1744336800",
            "timeend": "1744941600",
            "rewardinfo": "1_1726973_20",
            "userinfo": 211028,
            "userbitbuf": 12273,
            "stat": 2504020121
        },
        {
            "id": 28,
            "activityid": 1,
            "activityname": "0403纳多雷的复苏之旅",
            "title": "",
            "describe": "在灾厄等级6级难度下成功完成1次复苏之旅",
            "tasktype": 0,
            "value": 1,
            "time": 0,
            "time2": "",
            "timelimit": "1",
            "timestart": "1744336800",
            "timeend": "1744941600",
            "rewardinfo": "1_1726973_10",
            "userinfo": 211029,
            "userbitbuf": 12274,
            "stat": 2504020122
        },
        {
            "id": 29,
            "activityid": 1,
            "activityname": "0403纳多雷的复苏之旅",
            "title": "",
            "describe": "在灾厄等级7级难度下成功完成1次复苏之旅",
            "tasktype": 0,
            "value": 1,
            "time": 0,
            "time2": "",
            "timelimit": "1",
            "timestart": "1744336800",
            "timeend": "1744941600",
            "rewardinfo": "1_1726973_10",
            "userinfo": 211030,
            "userbitbuf": 12275,
            "stat": 2504020123
        },
        {
            "id": 30,
            "activityid": 1,
            "activityname": "0403纳多雷的复苏之旅",
            "title": "",
            "describe": "选择【矿物能量】祝福下成功完成1次复苏之旅挑战",
            "tasktype": 0,
            "value": 1,
            "time": 0,
            "time2": "",
            "timelimit": "1",
            "timestart": "1744336800",
            "timeend": "1744941600",
            "rewardinfo": "1_1726973_30",
            "userinfo": 211031,
            "userbitbuf": 12276,
            "stat": 2504020124
        },
        {
            "id": 31,
            "activityid": 1,
            "activityname": "0403纳多雷的复苏之旅",
            "title": "",
            "describe": "选择【植物能量】祝福下成功完成1次复苏之旅挑战",
            "tasktype": 0,
            "value": 1,
            "time": 0,
            "time2": "",
            "timelimit": "1",
            "timestart": "1744336800",
            "timeend": "1744941600",
            "rewardinfo": "1_1726973_30",
            "userinfo": 211032,
            "userbitbuf": 12277,
            "stat": 2504020125
        },
        {
            "id": 32,
            "activityid": 1,
            "activityname": "0403纳多雷的复苏之旅",
            "title": "",
            "describe": "选择【地热能量】祝福下成功完成1次复苏之旅挑战",
            "tasktype": 0,
            "value": 1,
            "time": 0,
            "time2": "",
            "timelimit": "1",
            "timestart": "1744336800",
            "timeend": "1744941600",
            "rewardinfo": "1_1726973_30",
            "userinfo": 211033,
            "userbitbuf": 12278,
            "stat": 2504020126
        },
        {
            "id": 33,
            "activityid": 1,
            "activityname": "0403纳多雷的复苏之旅",
            "title": "",
            "describe": "选择【灾厄试炼】诅咒下成功完成1次复苏之旅挑战",
            "tasktype": 0,
            "value": 1,
            "time": 0,
            "time2": "",
            "timelimit": "1",
            "timestart": "1744336800",
            "timeend": "1744941600",
            "rewardinfo": "1_1726973_30",
            "userinfo": 211034,
            "userbitbuf": 12279,
            "stat": 2504020127
        },
        {
            "id": 34,
            "activityid": 2,
            "activityname": "0418危险的数据舱",
            "title": "",
            "describe": "累计参与危险的数据舱1天",
            "tasktype": 0,
            "value": 1,
            "time": 0,
            "time2": "",
            "timelimit": "1",
            "timestart": "1744941600",
            "timeend": "1745546400",
            "rewardinfo": "1_2500004_1",
            "userinfo": 0,
            "userbitbuf": 0,
            "stat": 0
        },
        {
            "id": 35,
            "activityid": 2,
            "activityname": "0418危险的数据舱",
            "title": "",
            "describe": "累计参与危险的数据舱2天",
            "tasktype": 0,
            "value": 2,
            "time": 0,
            "time2": "",
            "timelimit": "1",
            "timestart": "1744941600",
            "timeend": "1745546400",
            "rewardinfo": "1_2500004_2",
            "userinfo": 0,
            "userbitbuf": 0,
            "stat": 0
        },
        {
            "id": 36,
            "activityid": 2,
            "activityname": "0418危险的数据舱",
            "title": "",
            "describe": "累计参与危险的数据舱3天",
            "tasktype": 0,
            "value": 3,
            "time": 0,
            "time2": "",
            "timelimit": "1",
            "timestart": "1744941600",
            "timeend": "1745546400",
            "rewardinfo": "1_300066_1",
            "userinfo": 0,
            "userbitbuf": 0,
            "stat": 0
        },
        {
            "id": 37,
            "activityid": 2,
            "activityname": "0418危险的数据舱",
            "title": "",
            "describe": "累计归档50个数据",
            "tasktype": 0,
            "value": 50,
            "time": 0,
            "time2": "",
            "timelimit": "1",
            "timestart": "1744941600",
            "timeend": "1745546400",
            "rewardinfo": "1_2500004_1",
            "userinfo": 0,
            "userbitbuf": 0,
            "stat": 0
        },
        {
            "id": 38,
            "activityid": 2,
            "activityname": "0418危险的数据舱",
            "title": "",
            "describe": "累计归档5个纯净数据",
            "tasktype": 0,
            "value": 5,
            "time": 0,
            "time2": "",
            "timelimit": "1",
            "timestart": "1744941600",
            "timeend": "1745546400",
            "rewardinfo": "1_2500004_1",
            "userinfo": 0,
            "userbitbuf": 0,
            "stat": 0
        },
        {
            "id": 39,
            "activityid": 2,
            "activityname": "0418危险的数据舱",
            "title": "",
            "describe": "累计归档5个加密数据",
            "tasktype": 0,
            "value": 5,
            "time": 0,
            "time2": "",
            "timelimit": "1",
            "timestart": "1744941600",
            "timeend": "1745546400",
            "rewardinfo": "1_1723855_50000",
            "userinfo": 0,
            "userbitbuf": 0,
            "stat": 0
        },
        {
            "id": 40,
            "activityid": 2,
            "activityname": "0418危险的数据舱",
            "title": "",
            "describe": "累计归档5个动态数据",
            "tasktype": 0,
            "value": 5,
            "time": 0,
            "time2": "",
            "timelimit": "1",
            "timestart": "1744941600",
            "timeend": "1745546400",
            "rewardinfo": "1_1723855_50000",
            "userinfo": 0,
            "userbitbuf": 0,
            "stat": 0
        },
        {
            "id": 41,
            "activityid": 2,
            "activityname": "0418危险的数据舱",
            "title": "",
            "describe": "累计归档5个碎片数据",
            "tasktype": 0,
            "value": 5,
            "time": 0,
            "time2": "",
            "timelimit": "1",
            "timestart": "1744941600",
            "timeend": "1745546400",
            "rewardinfo": "1_300697_5",
            "userinfo": 0,
            "userbitbuf": 0,
            "stat": 0
        },
        {
            "id": 42,
            "activityid": 2,
            "activityname": "0418危险的数据舱",
            "title": "",
            "describe": "累计归档5个病毒数据",
            "tasktype": 0,
            "value": 5,
            "time": 0,
            "time2": "",
            "timelimit": "1",
            "timestart": "1744941600",
            "timeend": "1745546400",
            "rewardinfo": "1_300697_5",
            "userinfo": 0,
            "userbitbuf": 0,
            "stat": 0
        },
        {
            "id": 43,
            "activityid": 3,
            "activityname": "0425勇者之塔逆转防线",
            "title": "防线新兵",
            "describe": "累计游玩1天逆转防线",
            "tasktype": 0,
            "value": 1,
            "time": 0,
            "time2": "",
            "timelimit": "1",
            "timestart": "1745546400",
            "timeend": "1746756000",
            "rewardinfo": "1_1727012_100",
            "userinfo": 211046,
            "userbitbuf": 12280,
            "stat": 0
        },
        {
            "id": 44,
            "activityid": 3,
            "activityname": "0425勇者之塔逆转防线",
            "title": "防线卫士",
            "describe": "累计游玩3天逆转防线",
            "tasktype": 0,
            "value": 3,
            "time": 0,
            "time2": "",
            "timelimit": "1",
            "timestart": "1745546400",
            "timeend": "1746756000",
            "rewardinfo": "1_1727012_200",
            "userinfo": 211046,
            "userbitbuf": 12281,
            "stat": 0
        },
        {
            "id": 45,
            "activityid": 3,
            "activityname": "0425勇者之塔逆转防线",
            "title": "防线高手",
            "describe": "累计游玩5天逆转防线",
            "tasktype": 0,
            "value": 5,
            "time": 0,
            "time2": "",
            "timelimit": "1",
            "timestart": "1745546400",
            "timeend": "1746756000",
            "rewardinfo": "1_1727012_300",
            "userinfo": 211046,
            "userbitbuf": 12282,
            "stat": 0
        },
        {
            "id": 46,
            "activityid": 3,
            "activityname": "0425勇者之塔逆转防线",
            "title": "防线专家",
            "describe": "累计游玩7天逆转防线",
            "tasktype": 0,
            "value": 7,
            "time": 0,
            "time2": "",
            "timelimit": "1",
            "timestart": "1745546400",
            "timeend": "1746756000",
            "rewardinfo": "1_1727012_400",
            "userinfo": 211046,
            "userbitbuf": 12283,
            "stat": 0
        },
        {
            "id": 47,
            "activityid": 3,
            "activityname": "0425勇者之塔逆转防线",
            "title": "防线大师",
            "describe": "累计游玩10天逆转防线",
            "tasktype": 0,
            "value": 10,
            "time": 0,
            "time2": "",
            "timelimit": "1",
            "timestart": "1745546400",
            "timeend": "1746756000",
            "rewardinfo": "1_1727012_500",
            "userinfo": 211046,
            "userbitbuf": 12284,
            "stat": 0
        },
        {
            "id": 48,
            "activityid": 3,
            "activityname": "0425勇者之塔逆转防线",
            "title": "初露锋芒",
            "describe": "累计游玩3次逆转防线",
            "tasktype": 0,
            "value": 3,
            "time": 0,
            "time2": "",
            "timelimit": "1",
            "timestart": "1745546400",
            "timeend": "1746756000",
            "rewardinfo": "1_1727012_100",
            "userinfo": 211047,
            "userbitbuf": 12285,
            "stat": 0
        },
        {
            "id": 49,
            "activityid": 3,
            "activityname": "0425勇者之塔逆转防线",
            "title": "渐入佳境",
            "describe": "累计游玩10次逆转防线",
            "tasktype": 0,
            "value": 10,
            "time": 0,
            "time2": "",
            "timelimit": "1",
            "timestart": "1745546400",
            "timeend": "1746756000",
            "rewardinfo": "1_1727012_100",
            "userinfo": 211047,
            "userbitbuf": 12286,
            "stat": 0
        },
        {
            "id": 50,
            "activityid": 3,
            "activityname": "0425勇者之塔逆转防线",
            "title": "逆转主宰者",
            "describe": "累计游玩30次逆转防线",
            "tasktype": 0,
            "value": 30,
            "time": 0,
            "time2": "",
            "timelimit": "1",
            "timestart": "1745546400",
            "timeend": "1746756000",
            "rewardinfo": "1_1727012_100",
            "userinfo": 211047,
            "userbitbuf": 12287,
            "stat": 0
        },
        {
            "id": 51,
            "activityid": 3,
            "activityname": "0425勇者之塔逆转防线",
            "title": "第一道防线",
            "describe": "首次招募一个精灵守卫",
            "tasktype": 0,
            "value": 1,
            "time": 0,
            "time2": "",
            "timelimit": "1",
            "timestart": "1745546400",
            "timeend": "1746756000",
            "rewardinfo": "1_1727012_50",
            "userinfo": 211048,
            "userbitbuf": 12288,
            "stat": 0
        },
        {
            "id": 52,
            "activityid": 3,
            "activityname": "0425勇者之塔逆转防线",
            "title": "训练初体验",
            "describe": "首次完成一次精灵训练",
            "tasktype": 0,
            "value": 1,
            "time": 0,
            "time2": "",
            "timelimit": "1",
            "timestart": "1745546400",
            "timeend": "1746756000",
            "rewardinfo": "1_1727012_50",
            "userinfo": 211049,
            "userbitbuf": 12289,
            "stat": 0
        },
        {
            "id": 53,
            "activityid": 3,
            "activityname": "0425勇者之塔逆转防线",
            "title": "首战告捷",
            "describe": "首次完成一次精灵防守",
            "tasktype": 0,
            "value": 1,
            "time": 0,
            "time2": "",
            "timelimit": "1",
            "timestart": "1745546400",
            "timeend": "1746756000",
            "rewardinfo": "1_1727012_50",
            "userinfo": 211050,
            "userbitbuf": 12290,
            "stat": 0
        },
        {
            "id": 54,
            "activityid": 3,
            "activityname": "0425勇者之塔逆转防线",
            "title": "金币满仓",
            "describe": "将【初始金币】升级到满级",
            "tasktype": 0,
            "value": 1,
            "time": 0,
            "time2": "",
            "timelimit": "1",
            "timestart": "1745546400",
            "timeend": "1746756000",
            "rewardinfo": "1_1727012_150",
            "userinfo": 211051,
            "userbitbuf": 12291,
            "stat": 0
        },
        {
            "id": 55,
            "activityid": 3,
            "activityname": "0425勇者之塔逆转防线",
            "title": "招募专家",
            "describe": "将【招募单价】升级到满级",
            "tasktype": 0,
            "value": 1,
            "time": 0,
            "time2": "",
            "timelimit": "1",
            "timestart": "1745546400",
            "timeend": "1746756000",
            "rewardinfo": "1_1727012_150",
            "userinfo": 211052,
            "userbitbuf": 12292,
            "stat": 0
        },
        {
            "id": 56,
            "activityid": 3,
            "activityname": "0425勇者之塔逆转防线",
            "title": "魔鬼教官",
            "describe": "将【守卫训练数量】升级到满级",
            "tasktype": 0,
            "value": 1,
            "time": 0,
            "time2": "",
            "timelimit": "1",
            "timestart": "1745546400",
            "timeend": "1746756000",
            "rewardinfo": "1_1727012_150",
            "userinfo": 211053,
            "userbitbuf": 12293,
            "stat": 0
        },
        {
            "id": 57,
            "activityid": 3,
            "activityname": "0425勇者之塔逆转防线",
            "title": "精打细算",
            "describe": "将【训练基础价格】升级到满级",
            "tasktype": 0,
            "value": 1,
            "time": 0,
            "time2": "",
            "timelimit": "1",
            "timestart": "1745546400",
            "timeend": "1746756000",
            "rewardinfo": "1_1727012_150",
            "userinfo": 211054,
            "userbitbuf": 12294,
            "stat": 0
        },
        {
            "id": 58,
            "activityid": 3,
            "activityname": "0425勇者之塔逆转防线",
            "title": "肯扎特之力",
            "describe": "将【肯扎特战斗力】升级到满级",
            "tasktype": 0,
            "value": 1,
            "time": 0,
            "time2": "",
            "timelimit": "1",
            "timestart": "1745546400",
            "timeend": "1746756000",
            "rewardinfo": "1_1727012_150",
            "userinfo": 211055,
            "userbitbuf": 12295,
            "stat": 0
        },
        {
            "id": 59,
            "activityid": 3,
            "activityname": "0425勇者之塔逆转防线",
            "title": "完美布局",
            "describe": "将【布置房间数量】升级到满级",
            "tasktype": 0,
            "value": 1,
            "time": 0,
            "time2": "",
            "timelimit": "1",
            "timestart": "1745546400",
            "timeend": "1746756000",
            "rewardinfo": "1_1727012_150",
            "userinfo": 211056,
            "userbitbuf": 12296,
            "stat": 0
        },
        {
            "id": 60,
            "activityid": 3,
            "activityname": "0425勇者之塔逆转防线",
            "title": "守卫小队",
            "describe": "单次游戏招募10个及以上的精灵守卫",
            "tasktype": 0,
            "value": 10,
            "time": 0,
            "time2": "",
            "timelimit": "1",
            "timestart": "1745546400",
            "timeend": "1746756000",
            "rewardinfo": "1_1727012_50",
            "userinfo": 211057,
            "userbitbuf": 12297,
            "stat": 0
        },
        {
            "id": 61,
            "activityid": 3,
            "activityname": "0425勇者之塔逆转防线",
            "title": "守卫军团",
            "describe": "单次游戏招募20个及以上的精灵守卫",
            "tasktype": 0,
            "value": 20,
            "time": 0,
            "time2": "",
            "timelimit": "1",
            "timestart": "1745546400",
            "timeend": "1746756000",
            "rewardinfo": "1_1727012_100",
            "userinfo": 211057,
            "userbitbuf": 12298,
            "stat": 0
        },
        {
            "id": 62,
            "activityid": 3,
            "activityname": "0425勇者之塔逆转防线",
            "title": "训练狂人",
            "describe": "单次游戏进行训练超过10次以上",
            "tasktype": 0,
            "value": 10,
            "time": 0,
            "time2": "",
            "timelimit": "1",
            "timestart": "1745546400",
            "timeend": "1746756000",
            "rewardinfo": "1_1727012_50",
            "userinfo": 211058,
            "userbitbuf": 12299,
            "stat": 0
        },
        {
            "id": 63,
            "activityid": 3,
            "activityname": "0425勇者之塔逆转防线",
            "title": "机械突破",
            "describe": "单次游戏进行训练超过20次以上",
            "tasktype": 0,
            "value": 20,
            "time": 0,
            "time2": "",
            "timelimit": "1",
            "timestart": "1745546400",
            "timeend": "1746756000",
            "rewardinfo": "1_1727012_100",
            "userinfo": 211058,
            "userbitbuf": 12300,
            "stat": 0
        },
        {
            "id": 64,
            "activityid": 3,
            "activityname": "0425勇者之塔逆转防线",
            "title": "挑战者杀手",
            "describe": "单次游戏击败了5个及以上的挑战者",
            "tasktype": 0,
            "value": 5,
            "time": 0,
            "time2": "",
            "timelimit": "1",
            "timestart": "1745546400",
            "timeend": "1746756000",
            "rewardinfo": "1_1727012_50",
            "userinfo": 211059,
            "userbitbuf": 12301,
            "stat": 0
        },
        {
            "id": 65,
            "activityid": 3,
            "activityname": "0425勇者之塔逆转防线",
            "title": "精英粉碎者",
            "describe": "单次游戏击败了10个及以上的挑战者",
            "tasktype": 0,
            "value": 10,
            "time": 0,
            "time2": "",
            "timelimit": "1",
            "timestart": "1745546400",
            "timeend": "1746756000",
            "rewardinfo": "1_1727012_100",
            "userinfo": 211059,
            "userbitbuf": 12302,
            "stat": 0
        },
        {
            "id": 66,
            "activityid": 3,
            "activityname": "0425勇者之塔逆转防线",
            "title": "传奇终结者",
            "describe": "单次游戏击败了15个及以上的挑战者",
            "tasktype": 0,
            "value": 15,
            "time": 0,
            "time2": "",
            "timelimit": "1",
            "timestart": "1745546400",
            "timeend": "1746756000",
            "rewardinfo": "1_1727012_100",
            "userinfo": 211059,
            "userbitbuf": 12303,
            "stat": 0
        },
        {
            "id": 67,
            "activityid": 3,
            "activityname": "0425勇者之塔逆转防线",
            "title": "荣誉观测者",
            "describe": "累计击败50个挑战者",
            "tasktype": 0,
            "value": 50,
            "time": 0,
            "time2": "",
            "timelimit": "1",
            "timestart": "1745546400",
            "timeend": "1746756000",
            "rewardinfo": "1_1727012_100",
            "userinfo": 211060,
            "userbitbuf": 12304,
            "stat": 0
        },
        {
            "id": 68,
            "activityid": 3,
            "activityname": "0425勇者之塔逆转防线",
            "title": "荣誉观测者S",
            "describe": "累计击败100个挑战者",
            "tasktype": 0,
            "value": 100,
            "time": 0,
            "time2": "",
            "timelimit": "1",
            "timestart": "1745546400",
            "timeend": "1746756000",
            "rewardinfo": "1_1727012_200",
            "userinfo": 211060,
            "userbitbuf": 12305,
            "stat": 0
        },
        {
            "id": 69,
            "activityid": 4,
            "activityname": "0516电力供给支援",
            "title": "",
            "describe": "完成【能源中心】的电力供给任务",
            "tasktype": 0,
            "value": 1,
            "time": 0,
            "time2": "",
            "timelimit": "1",
            "timestart": "1747360800",
            "timeend": "1747965600",
            "rewardinfo": "1_2500004_1",
            "userinfo": 0,
            "userbitbuf": 0,
            "stat": 0
        },
        {
            "id": 70,
            "activityid": 4,
            "activityname": "0516电力供给支援",
            "title": "",
            "describe": "完成【机械室】的电力供给任务",
            "tasktype": 0,
            "value": 1,
            "time": 0,
            "time2": "",
            "timelimit": "1",
            "timestart": "1747360800",
            "timeend": "1747965600",
            "rewardinfo": "1_300878_2",
            "userinfo": 0,
            "userbitbuf": 0,
            "stat": 0
        },
        {
            "id": 71,
            "activityid": 4,
            "activityname": "0516电力供给支援",
            "title": "",
            "describe": "完成【船长室】的电力供给任务",
            "tasktype": 0,
            "value": 1,
            "time": 0,
            "time2": "",
            "timelimit": "1",
            "timestart": "1747360800",
            "timeend": "1747965600",
            "rewardinfo": "1_2500004_1",
            "userinfo": 0,
            "userbitbuf": 0,
            "stat": 0
        },
        {
            "id": 72,
            "activityid": 4,
            "activityname": "0516电力供给支援",
            "title": "",
            "describe": "完成【传送舱】的电力供给任务",
            "tasktype": 0,
            "value": 1,
            "time": 0,
            "time2": "",
            "timelimit": "1",
            "timestart": "1747360800",
            "timeend": "1747965600",
            "rewardinfo": "1_300790_2",
            "userinfo": 0,
            "userbitbuf": 0,
            "stat": 0
        },
        {
            "id": 73,
            "activityid": 4,
            "activityname": "0516电力供给支援",
            "title": "",
            "describe": "完成【精灵中心】的电力供给任务",
            "tasktype": 0,
            "value": 1,
            "time": 0,
            "time2": "",
            "timelimit": "1",
            "timestart": "1747360800",
            "timeend": "1747965600",
            "rewardinfo": "1_300066_1",
            "userinfo": 0,
            "userbitbuf": 0,
            "stat": 0
        },
        {
            "id": 74,
            "activityid": 4,
            "activityname": "0516电力供给支援",
            "title": "",
            "describe": "完成【瞭望舱】的电力供给任务",
            "tasktype": 0,
            "value": 1,
            "time": 0,
            "time2": "",
            "timelimit": "1",
            "timestart": "1747360800",
            "timeend": "1747965600",
            "rewardinfo": "1_2500004_1",
            "userinfo": 0,
            "userbitbuf": 0,
            "stat": 0
        },
        {
            "id": 75,
            "activityid": 4,
            "activityname": "0516电力供给支援",
            "title": "",
            "describe": "完成【教官办公室】的电力供给任务",
            "tasktype": 0,
            "value": 1,
            "time": 0,
            "time2": "",
            "timelimit": "1",
            "timestart": "1747360800",
            "timeend": "1747965600",
            "rewardinfo": "1_300790_2",
            "userinfo": 0,
            "userbitbuf": 0,
            "stat": 0
        },
        {
            "id": 76,
            "activityid": 4,
            "activityname": "0516电力供给支援",
            "title": "",
            "describe": "完成【资料室】的电力供给任务",
            "tasktype": 0,
            "value": 1,
            "time": 0,
            "time2": "",
            "timelimit": "1",
            "timestart": "1747360800",
            "timeend": "1747965600",
            "rewardinfo": "1_300878_2",
            "userinfo": 0,
            "userbitbuf": 0,
            "stat": 0
        },
        {
            "id": 77,
            "activityid": 4,
            "activityname": "0516电力供给支援",
            "title": "",
            "describe": "完成【活动中心】的电力供给任务",
            "tasktype": 0,
            "value": 1,
            "time": 0,
            "time2": "",
            "timelimit": "1",
            "timestart": "1747360800",
            "timeend": "1747965600",
            "rewardinfo": "1_2500004_1",
            "userinfo": 0,
            "userbitbuf": 0,
            "stat": 0
        },
        {
            "id": 78,
            "activityid": 4,
            "activityname": "0516电力供给支援",
            "title": "",
            "describe": "完成【VIP殿堂】的电力供给任务",
            "tasktype": 0,
            "value": 1,
            "time": 0,
            "time2": "",
            "timelimit": "1",
            "timestart": "1747360800",
            "timeend": "1747965600",
            "rewardinfo": "1_300790_1",
            "userinfo": 0,
            "userbitbuf": 0,
            "stat": 0
        },
        {
            "id": 79,
            "activityid": 4,
            "activityname": "0516电力供给支援",
            "title": "",
            "describe": "完成【荣誉大厅】的电力供给任务",
            "tasktype": 0,
            "value": 1,
            "time": 0,
            "time2": "",
            "timelimit": "1",
            "timestart": "1747360800",
            "timeend": "1747965600",
            "rewardinfo": "1_300878_1",
            "userinfo": 0,
            "userbitbuf": 0,
            "stat": 0
        },
        {
            "id": 80,
            "activityid": 4,
            "activityname": "0516电力供给支援",
            "title": "",
            "describe": "完成【放映厅】的电力供给任务",
            "tasktype": 0,
            "value": 1,
            "time": 0,
            "time2": "",
            "timelimit": "1",
            "timestart": "1747360800",
            "timeend": "1747965600",
            "rewardinfo": "1_300790_1",
            "userinfo": 0,
            "userbitbuf": 0,
            "stat": 0
        },
        {
            "id": 81,
            "activityid": 4,
            "activityname": "0516电力供给支援",
            "title": "",
            "describe": "完成【瞭望露台】的电力供给任务",
            "tasktype": 0,
            "value": 1,
            "time": 0,
            "time2": "",
            "timelimit": "1",
            "timestart": "1747360800",
            "timeend": "1747965600",
            "rewardinfo": "1_300878_1",
            "userinfo": 0,
            "userbitbuf": 0,
            "stat": 0
        },
        {
            "id": 101,
            "activityid": 5,
            "activityname": "0530晶骰传说",
            "title": "",
            "describe": "点亮所有天赋树",
            "tasktype": 0,
            "value": 1,
            "time": 0,
            "time2": "",
            "timelimit": "1",
            "timestart": "1748534400",
            "timeend": "1751594400",
            "rewardinfo": "1_1727088_500",
            "userinfo": 211061,
            "userbitbuf": 9910,
            "stat": 0
        },
        {
            "id": 102,
            "activityid": 5,
            "activityname": "0530晶骰传说",
            "title": "",
            "describe": "取得一次SSS级评价",
            "tasktype": 0,
            "value": 1,
            "time": 0,
            "time2": "",
            "timelimit": "1",
            "timestart": "1748534400",
            "timeend": "1751594400",
            "rewardinfo": "1_1727088_200",
            "userinfo": 211062,
            "userbitbuf": 9911,
            "stat": 0
        },
        {
            "id": 103,
            "activityid": 5,
            "activityname": "0530晶骰传说",
            "title": "",
            "describe": "在【废墟边缘】击败西塔·能源型",
            "tasktype": 0,
            "value": 1,
            "time": 0,
            "time2": "",
            "timelimit": "1",
            "timestart": "1748534400",
            "timeend": "1751594400",
            "rewardinfo": "1_1727088_300",
            "userinfo": 211063,
            "userbitbuf": 9912,
            "stat": 0
        },
        {
            "id": 104,
            "activityid": 5,
            "activityname": "0530晶骰传说",
            "title": "",
            "describe": "在【废墟边缘】击败卡塔·武装型",
            "tasktype": 0,
            "value": 1,
            "time": 0,
            "time2": "",
            "timelimit": "1",
            "timestart": "1748534400",
            "timeend": "1751594400",
            "rewardinfo": "1_1727088_300",
            "userinfo": 211064,
            "userbitbuf": 9913,
            "stat": 0
        },
        {
            "id": 105,
            "activityid": 5,
            "activityname": "0530晶骰传说",
            "title": "",
            "describe": "在【废墟边缘】击败奇塔·解算型",
            "tasktype": 0,
            "value": 1,
            "time": 0,
            "time2": "",
            "timelimit": "1",
            "timestart": "1748534400",
            "timeend": "1751594400",
            "rewardinfo": "1_1727088_300",
            "userinfo": 211065,
            "userbitbuf": 9914,
            "stat": 0
        },
        {
            "id": 106,
            "activityid": 5,
            "activityname": "0530晶骰传说",
            "title": "",
            "describe": "在【水银沙城】击败梦魇塔奇拉顿",
            "tasktype": 0,
            "value": 1,
            "time": 0,
            "time2": "",
            "timelimit": "1",
            "timestart": "1748534400",
            "timeend": "1751594400",
            "rewardinfo": "1_1727088_500",
            "userinfo": 211066,
            "userbitbuf": 9915,
            "stat": 0
        },
        {
            "id": 107,
            "activityid": 5,
            "activityname": "0530晶骰传说",
            "title": "",
            "describe": "在【水银沙城】击败梦魇尼斯克",
            "tasktype": 0,
            "value": 1,
            "time": 0,
            "time2": "",
            "timelimit": "1",
            "timestart": "1748534400",
            "timeend": "1751594400",
            "rewardinfo": "1_1727088_500",
            "userinfo": 211067,
            "userbitbuf": 9916,
            "stat": 0
        },
        {
            "id": 108,
            "activityid": 6,
            "activityname": "0606琉璃幻梦",
            "title": "",
            "describe": "获得神裁·雷伊",
            "tasktype": 0,
            "value": 1,
            "time": 0,
            "time2": "",
            "timelimit": "1",
            "timestart": "1749175200",
            "timeend": "1751594400",
            "rewardinfo": "1_1727081_60",
            "userinfo": 140057,
            "userbitbuf": 11003,
            "stat": 0
        },
        {
            "id": 109,
            "activityid": 6,
            "activityname": "0606琉璃幻梦",
            "title": "",
            "describe": "获得神决·盖亚",
            "tasktype": 0,
            "value": 1,
            "time": 0,
            "time2": "",
            "timelimit": "1",
            "timestart": "1749175200",
            "timeend": "1751594400",
            "rewardinfo": "1_1727082_40",
            "userinfo": 140058,
            "userbitbuf": 11004,
            "stat": 0
        },
        {
            "id": 110,
            "activityid": 6,
            "activityname": "0606琉璃幻梦",
            "title": "",
            "describe": "启程之忆活动点亮14个梦泡",
            "tasktype": 0,
            "value": 14,
            "time": 0,
            "time2": "",
            "timelimit": "1",
            "timestart": "1749175200",
            "timeend": "1751594400",
            "rewardinfo": "1_1727083_40",
            "userinfo": 140059,
            "userbitbuf": 11005,
            "stat": 0
        },
        {
            "id": 111,
            "activityid": 6,
            "activityname": "0606琉璃幻梦",
            "title": "",
            "describe": "晶骰传说活动中累计获得10个晶脉核心",
            "tasktype": 0,
            "value": 10,
            "time": 0,
            "time2": "",
            "timelimit": "1",
            "timestart": "1749175200",
            "timeend": "1751594400",
            "rewardinfo": "2_42568_1;2_42569_1;2_42570_1",
            "userinfo": 140073,
            "userbitbuf": 11006,
            "stat": 0
        },
        {
            "id": 112,
            "activityid": 6,
            "activityname": "0606琉璃幻梦",
            "title": "",
            "describe": "晶骰传说活动中累计获得20个晶脉核心",
            "tasktype": 0,
            "value": 20,
            "time": 0,
            "time2": "",
            "timelimit": "1",
            "timestart": "1749175200",
            "timeend": "1751594400",
            "rewardinfo": "1_300066_1",
            "userinfo": 140073,
            "userbitbuf": 11007,
            "stat": 0
        },
        {
            "id": 113,
            "activityid": 7,
            "activityname": "0613琉璃幻梦",
            "title": "",
            "describe": "噩梦回响活动挑战BOSS6次",
            "tasktype": 0,
            "value": 6,
            "time": 0,
            "time2": "",
            "timelimit": "1",
            "timestart": "1749780000",
            "timeend": "1751594400",
            "rewardinfo": "1_300066_1",
            "userinfo": 140062,
            "userbitbuf": 11008,
            "stat": 0
        },
        {
            "id": 114,
            "activityid": 7,
            "activityname": "0613琉璃幻梦",
            "title": "",
            "describe": "噩梦回响活动挑战BOSS12次",
            "tasktype": 0,
            "value": 12,
            "time": 0,
            "time2": "",
            "timelimit": "1",
            "timestart": "1749780000",
            "timeend": "1751594400",
            "rewardinfo": "2_42571_1;2_42572_1;2_42573_1",
            "userinfo": 140062,
            "userbitbuf": 11009,
            "stat": 0
        },
        {
            "id": 115,
            "activityid": 7,
            "activityname": "0613琉璃幻梦",
            "title": "",
            "describe": "在晶骰传说的【冒险商店】累计消耗3000晶符礼券",
            "tasktype": 0,
            "value": 3000,
            "time": 0,
            "time2": "",
            "timelimit": "1",
            "timestart": "1749780000",
            "timeend": "1751594400",
            "rewardinfo": "1_1727081_60",
            "userinfo": 140064,
            "userbitbuf": 11010,
            "stat": 0
        },
        {
            "id": 116,
            "activityid": 7,
            "activityname": "0613琉璃幻梦",
            "title": "",
            "describe": "探索露希欧星活动中参与岩层清理累计完成10次",
            "tasktype": 0,
            "value": 10,
            "time": 0,
            "time2": "",
            "timelimit": "1",
            "timestart": "1749780000",
            "timeend": "1751594400",
            "rewardinfo": "1_1727082_40",
            "userinfo": 140065,
            "userbitbuf": 11011,
            "stat": 0
        },
        {
            "id": 117,
            "activityid": 7,
            "activityname": "0613琉璃幻梦",
            "title": "",
            "describe": "探索露希欧星活动中参与海沟宝藏累计完成10次",
            "tasktype": 0,
            "value": 10,
            "time": 0,
            "time2": "",
            "timelimit": "1",
            "timestart": "1749780000",
            "timeend": "1751594400",
            "rewardinfo": "1_1727083_40",
            "userinfo": 140066,
            "userbitbuf": 11012,
            "stat": 0
        },
        {
            "id": 118,
            "activityid": 8,
            "activityname": "0620琉璃幻梦",
            "title": "",
            "describe": "噩梦回响活动挑战BOSS20次",
            "tasktype": 0,
            "value": 20,
            "time": 0,
            "time2": "",
            "timelimit": "1",
            "timestart": "1750384800",
            "timeend": "1751594400",
            "rewardinfo": "1_300746_1",
            "userinfo": 140062,
            "userbitbuf": 11013,
            "stat": 0
        },
        {
            "id": 119,
            "activityid": 8,
            "activityname": "0620琉璃幻梦",
            "title": "",
            "describe": "在晶骰传说的【冒险商店】累计消耗6000晶符礼券",
            "tasktype": 0,
            "value": 6000,
            "time": 0,
            "time2": "",
            "timelimit": "1",
            "timestart": "1750384800",
            "timeend": "1751594400",
            "rewardinfo": "2_42574_1;2_42575_1",
            "userinfo": 140064,
            "userbitbuf": 11014,
            "stat": 0
        },
        {
            "id": 120,
            "activityid": 8,
            "activityname": "0620琉璃幻梦",
            "title": "",
            "describe": "完成剧情历史的余烬2-9",
            "tasktype": 0,
            "value": 1,
            "time": 0,
            "time2": "",
            "timelimit": "1",
            "timestart": "1750384800",
            "timeend": "1751594400",
            "rewardinfo": "1_1726992_300",
            "userinfo": 140071,
            "userbitbuf": 11015,
            "stat": 0
        },
        {
            "id": 121,
            "activityid": 8,
            "activityname": "0620琉璃幻梦",
            "title": "",
            "describe": "探索露希欧星活动中参与岩层清理累计完成15次",
            "tasktype": 0,
            "value": 15,
            "time": 0,
            "time2": "",
            "timelimit": "1",
            "timestart": "1750384800",
            "timeend": "1751594400",
            "rewardinfo": "1_1726992_200",
            "userinfo": 140065,
            "userbitbuf": 11016,
            "stat": 0
        },
        {
            "id": 122,
            "activityid": 8,
            "activityname": "0620琉璃幻梦",
            "title": "",
            "describe": "探索露希欧星活动中参与海沟宝藏累计完成15次",
            "tasktype": 0,
            "value": 15,
            "time": 0,
            "time2": "",
            "timelimit": "1",
            "timestart": "1750384800",
            "timeend": "1751594400",
            "rewardinfo": "1_1723854_10000",
            "userinfo": 140066,
            "userbitbuf": 11017,
            "stat": 0
        },
        {
            "id": 123,
            "activityid": 5,
            "activityname": "0530晶骰传说",
            "title": "",
            "describe": "在【虹晶秘境】击败魇魔",
            "tasktype": 0,
            "value": 1,
            "time": 0,
            "time2": "",
            "timelimit": "1",
            "timestart": "1749175200",
            "timeend": "1751594400",
            "rewardinfo": "1_1727088_500",
            "userinfo": 211097,
            "userbitbuf": 9917,
            "stat": 0
        },
        {
            "id": 124,
            "activityid": 5,
            "activityname": "0530晶骰传说",
            "title": "",
            "describe": "在【虹晶秘境】击败绝魇魔女",
            "tasktype": 0,
            "value": 1,
            "time": 0,
            "time2": "",
            "timelimit": "1",
            "timestart": "1749175200",
            "timeend": "1751594400",
            "rewardinfo": "1_1727088_500",
            "userinfo": 211098,
            "userbitbuf": 9918,
            "stat": 0
        },
        {
            "id": 125,
            "activityid": 5,
            "activityname": "0530晶骰传说",
            "title": "",
            "describe": "击败咤克斯的幻影",
            "tasktype": 0,
            "value": 1,
            "time": 0,
            "time2": "",
            "timelimit": "1",
            "timestart": "1749780000",
            "timeend": "1751594400",
            "rewardinfo": "1_1727088_500",
            "userinfo": 211099,
            "userbitbuf": 9919,
            "stat": 0
        },
        {
            "id": 126,
            "activityid": 9,
            "activityname": "0704深海巨兽大对决",
            "title": "",
            "describe": "将布贝巴拉提升至深海一霸评级",
            "tasktype": 0,
            "value": 1,
            "time": 0,
            "time2": "",
            "timelimit": "1",
            "timestart": "1751594400",
            "timeend": "1752804000",
            "rewardinfo": "1_1706926_5",
            "userinfo": 105923,
            "userbitbuf": 9928,
            "stat": 0
        },
        {
            "id": 127,
            "activityid": 9,
            "activityname": "0704深海巨兽大对决",
            "title": "",
            "describe": "将鞘盾龙鱼提升至深海一霸评级",
            "tasktype": 0,
            "value": 1,
            "time": 0,
            "time2": "",
            "timelimit": "1",
            "timestart": "1751594400",
            "timeend": "1752804000",
            "rewardinfo": "1_1706924_5",
            "userinfo": 105924,
            "userbitbuf": 9929,
            "stat": 0
        },
        {
            "id": 128,
            "activityid": 9,
            "activityname": "0704深海巨兽大对决",
            "title": "",
            "describe": "将斯弗洛浦亚提升至深海一霸评级",
            "tasktype": 0,
            "value": 1,
            "time": 0,
            "time2": "",
            "timelimit": "1",
            "timestart": "1751594400",
            "timeend": "1752804000",
            "rewardinfo": "1_1706925_5",
            "userinfo": 105925,
            "userbitbuf": 9930,
            "stat": 0
        },
        {
            "id": 129,
            "activityid": 9,
            "activityname": "0704深海巨兽大对决",
            "title": "",
            "describe": "击败首领级布贝巴拉",
            "tasktype": 0,
            "value": 1,
            "time": 0,
            "time2": "",
            "timelimit": "1",
            "timestart": "1751594400",
            "timeend": "1752804000",
            "rewardinfo": "1_2500003_2",
            "userinfo": 105926,
            "userbitbuf": 9931,
            "stat": 0
        },
        {
            "id": 130,
            "activityid": 9,
            "activityname": "0704深海巨兽大对决",
            "title": "",
            "describe": "击败首领级鞘盾龙鱼",
            "tasktype": 0,
            "value": 1,
            "time": 0,
            "time2": "",
            "timelimit": "1",
            "timestart": "1751594400",
            "timeend": "1752804000",
            "rewardinfo": "1_2500003_3",
            "userinfo": 105927,
            "userbitbuf": 9932,
            "stat": 0
        },
        {
            "id": 131,
            "activityid": 9,
            "activityname": "0704深海巨兽大对决",
            "title": "",
            "describe": "击败首领级斯弗洛浦亚",
            "tasktype": 0,
            "value": 1,
            "time": 0,
            "time2": "",
            "timelimit": "1",
            "timestart": "1751594400",
            "timeend": "1752804000",
            "rewardinfo": "1_300066_1",
            "userinfo": 105928,
            "userbitbuf": 9933,
            "stat": 0
        },
        {
            "id": 132,
            "activityid": 9,
            "activityname": "",
            "title": "",
            "describe": "",
            "tasktype": 0,
            "value": 0,
            "time": 0,
            "time2": "",
            "timelimit": "1",
            "timestart": "1752199200",
            "timeend": "1752804000",
            "rewardinfo": "",
            "userinfo": 105929,
            "userbitbuf": 9934,
            "stat": 0
        },
        {
            "id": 133,
            "activityid": 9,
            "activityname": "",
            "title": "",
            "describe": "",
            "tasktype": 0,
            "value": 0,
            "time": 0,
            "time2": "",
            "timelimit": "1",
            "timestart": "1752199200",
            "timeend": "1752804000",
            "rewardinfo": "",
            "userinfo": 105930,
            "userbitbuf": 9935,
            "stat": 0
        },
        {
            "id": 134,
            "activityid": 9,
            "activityname": "",
            "title": "",
            "describe": "",
            "tasktype": 0,
            "value": 0,
            "time": 0,
            "time2": "",
            "timelimit": "1",
            "timestart": "1752199200",
            "timeend": "1752804000",
            "rewardinfo": "",
            "userinfo": 105931,
            "userbitbuf": 9936,
            "stat": 0
        }
    ]
}