{
    "data": [
        {
            "id": 1,
            "rewardtype": "1_1",
            "rewardid": "9_1",
            "rewardnum": "50_1000",
            "raidunlocktext": "出战精灵全部存活的情况下击败所有BOSS，即可开启本层扫荡功能",
            "raidunlockarg": 0,
            "bosslist": "5582_5584_5581",
            "sebossid": "17517_17518_17516"
        },
        {
            "id": 2,
            "rewardtype": "1_1",
            "rewardid": "9_1",
            "rewardnum": "60_2000",
            "raidunlocktext": "出战精灵全部存活的情况下击败所有BOSS，即可开启本层扫荡功能",
            "raidunlockarg": 0,
            "bosslist": "5582_5584_5581",
            "sebossid": "17520_17521_17519"
        },
        {
            "id": 3,
            "rewardtype": "1_1",
            "rewardid": "9_1",
            "rewardnum": "70_3000",
            "raidunlocktext": "10回合内击败所有BOSS，即可开启本层扫荡功能",
            "raidunlockarg": 10,
            "bosslist": "5584_5581_5583_5586",
            "sebossid": "17524_17522_17523_17525"
        },
        {
            "id": 4,
            "rewardtype": "1_1",
            "rewardid": "9_1",
            "rewardnum": "80_4000",
            "raidunlocktext": "自身出战精灵血量不低于400时击败最终BOSS，即可开启本层扫荡功能",
            "raidunlockarg": 400,
            "bosslist": "5584_5581_5583_5586",
            "sebossid": "17528_17526_17527_17529"
        },
        {
            "id": 5,
            "rewardtype": "1_1",
            "rewardid": "9_1",
            "rewardnum": "90_5000",
            "raidunlocktext": "8回合内击败所有BOSS，即可开启本层扫荡功能",
            "raidunlockarg": 8,
            "bosslist": "5584_5585_5583_5586_5587",
            "sebossid": "17531_17532_17530_17533_17534"
        },
        {
            "id": 6,
            "rewardtype": "1_1",
            "rewardid": "9_1",
            "rewardnum": "100_6000",
            "raidunlocktext": "自身出战精灵血量不低于500时击败最终BOSS，即可开启本层扫荡功能",
            "raidunlockarg": 500,
            "bosslist": "5584_5585_5583_5586_5587",
            "sebossid": "17536_17537_17535_17538_17539"
        }
    ]
}